{
  "cli": {
    "version": ">= 7.5.0"
  },
  "build": {
    "development": {
      "developmentClient": true,
      "distribution": "internal"
    },
    "preview": {
      "developmentClient": true,
      "android": {
        "buildType": "apk",
        "gradleCommand": ":app:assembleRelease"
      },
      "env": {
        "EXPO_PUBLIC_API_KEY": "1602c62567a4966a7a006133a96ebc32"
      },
      "distribution": "internal"
    },
    "production": {}
  },
  "submit": {
    "production": {}
  }
}
